pamet/__init__.py
pamet/channels.py
pamet/commands.py
pamet/config.py
pamet/constants.py
pamet/note_view_lib.py
pamet/persistence_manager.py
pamet/actions/map_page.py
pamet/actions/note.py
pamet/actions/other.py
pamet/actions/tab.py
pamet/actions/window.py
pamet/desktop_app/__init__.py
pamet/desktop_app/app.py
pamet/desktop_app/config.py
pamet/desktop_app/icon_cache.py
pamet/desktop_app/init_config.py
pamet/desktop_app/main.py
pamet/desktop_app/mime_data_utils.py
pamet/desktop_app/util.py
pamet/model/arrow.py
pamet/model/card_note.py
pamet/model/image_note.py
pamet/model/note.py
pamet/model/op_list_note.py
pamet/model/page.py
pamet/model/page_child.py
pamet/model/script_note.py
pamet/model/text_note.py
pamet/resources/appdata.xml
pamet/resources/privacy-policy.md
pamet/resources/desktop_entries/pamet.desktop
"pamet/resources/fonts/OpenSans-VariableFont_wdth,wght.ttf"
pamet/resources/icons/delete-bin-line.svg
pamet/resources/icons/image-line.svg
pamet/resources/icons/link.svg
pamet/resources/icons/more-2-line.svg
pamet/resources/icons/pamet-icon.ico
pamet/resources/icons/pamet-icon.png
pamet/resources/icons/plus.svg
pamet/resources/icons/text.svg
pamet/resources/script_templates/bash.sh
pamet/resources/script_templates/python.py
pamet/resources/static_page_src/script.js
pamet/resources/static_page_src/style.css
pamet/server/__main__.py
pamet/services/backup.py
pamet/services/clipboard.py
pamet/services/file_note_watcher.py
pamet/services/local_server.py
pamet/services/media_store.py
pamet/services/other_pages_list_update.py
pamet/services/script_runner.py
pamet/services/undo.py
pamet/services/search/base.py
pamet/services/search/fuzzy.py
pamet/services/search/plain.py
pamet/services/search/semantic.py
pamet/storage/__init__.py
pamet/storage/base_repository.py
pamet/storage/pamet_in_memory_repo.py
pamet/storage/file_system/legacy.py
pamet/storage/file_system/repository.py
pamet/util/__init__.py
pamet/util/url.py
pamet/views/selector_widget.py
pamet-4.0.0a15.dist-info/LICENSE
pamet-4.0.0a15.dist-info/METADATA
pamet-4.0.0a15.dist-info/WHEEL
pamet-4.0.0a15.dist-info/entry_points.txt
pamet-4.0.0a15.dist-info/top_level.txt
pamet-4.0.0a15.dist-info/RECORD
