Metadata-Version: 2.1
Name: pamet
Version: 4.0.0a15
Summary: An app for organizing notes and thoughts
Author-email: Petko Dichev <pditchev@gmail.com>
License: GPLv3
Classifier: Development Status :: 3 - Alpha
Classifier: Programming Language :: Python :: 3
Classifier: License :: OSI Approved :: GNU General Public License v3 (GPLv3)
Classifier: Operating System :: OS Independent
Requires-Python: >=3.10
License-File: LICENSE
Requires-Dist: PySide6
Requires-Dist: python-fusion (>=0.7.5)
Requires-Dist: click
Requires-Dist: python-slugify
Requires-Dist: thefuzz
Requires-Dist: peewee
Requires-Dist: pillow
Requires-Dist: watchdog
Requires-Dist: fastapi
Requires-Dist: uvicorn
Requires-Dist: sqlitedict
Requires-Dist: requests
